TichonetUnit10V2/U10_facenet_utils.py
TichonetUnit10V2/U10_style_transfer_utils.py
TichonetUnit10V2/U10_yolo3_utils.py
TichonetUnit10V2/__init__.py
TichonetUnit10V2/utils.py
TichonetUnit10V2/datasets/data.mat
TichonetUnit10V2/datasets/test_signs.h5
TichonetUnit10V2/datasets/train_signs.h5
TichonetUnit10V2/datasets/cat_nocat/test_catvnoncat.h5
TichonetUnit10V2/datasets/cat_nocat/train_catvnoncat.h5
tichonetunit10v2-0.0.1.dist-info/METADATA
tichonetunit10v2-0.0.1.dist-info/WHEEL
tichonetunit10v2-0.0.1.dist-info/licenses/LICENSE
tichonetunit10v2-0.0.1.dist-info/RECORD
